{
    "name": "Product",
    "fields": [
        {
            "fieldName": "title",
            "fieldType": "String",
            "fieldValidateRules": [
                "required"
            ]
        },
        {
            "fieldName": "keywords",
            "fieldType": "String"
        },
        {
            "fieldName": "description",
            "fieldType": "String"
        },
        {
            "fieldName": "rating",
            "fieldType": "Integer"
        },
        {
            "fieldName": "dateAdded",
            "fieldType": "LocalDate"
        },
        {
            "fieldName": "dateModified",
            "fieldType": "LocalDate"
        }
    ],
    "relationships": [
        {
            "relationshipType": "many-to-many",
            "relationshipName": "category",
            "otherEntityName": "category",
            "ownerSide": false,
            "otherEntityRelationshipName": "product"
        }
    ],
    "changelogDate": "20190214141716",
    "entityTableName": "product",
    "dto": "no",
    "pagination": "infinite-scroll",
    "service": "no",
    "jpaMetamodelFiltering": false,
    "fluentMethods": true,
    "clientRootFolder": "",
    "applications": "*"
}